k_diffusion/__init__.py
k_diffusion/augmentation.py
k_diffusion/config.py
k_diffusion/evaluation.py
k_diffusion/external.py
k_diffusion/gns.py
k_diffusion/layers.py
k_diffusion/sampling.py
k_diffusion/utils.py
k_diffusion/models/__init__.py
k_diffusion/models/axial_rope.py
k_diffusion/models/flags.py
k_diffusion/models/image_transformer_v1.py
k_diffusion/models/image_v1.py
k_diffusion-0.1.1.post1.dist-info/LICENSE
k_diffusion-0.1.1.post1.dist-info/METADATA
k_diffusion-0.1.1.post1.dist-info/WHEEL
k_diffusion-0.1.1.post1.dist-info/top_level.txt
k_diffusion-0.1.1.post1.dist-info/RECORD
