Metadata-Version: 2.1
Name: k-diffusion
Version: 0.1.1.post1
Summary: Karras et al. (2022) diffusion models for PyTorch
Home-page: https://github.com/crowsonkb/k-diffusion
Author: Katherine Crowson
Author-email: crowsonkb@gmail.com
License: MIT
Platform: UNKNOWN
